odoo8_addon_l10n_es_aeat_mod340_type0-8.0.1.0.0.99.dev10-py3.6-nspkg.pth
odoo_addons/l10n_es_aeat_mod340_type0/__init__.py
odoo_addons/l10n_es_aeat_mod340_type0/__openerp__.py
odoo_addons/l10n_es_aeat_mod340_type0/mod340_view.xml
odoo_addons/l10n_es_aeat_mod340_type0/i18n/ca.po
odoo_addons/l10n_es_aeat_mod340_type0/i18n/es.po
odoo_addons/l10n_es_aeat_mod340_type0/i18n/eu.po
odoo_addons/l10n_es_aeat_mod340_type0/i18n/fr.po
odoo_addons/l10n_es_aeat_mod340_type0/i18n/gl.po
odoo_addons/l10n_es_aeat_mod340_type0/i18n/hr.po
odoo_addons/l10n_es_aeat_mod340_type0/i18n/l10n_es_aeat_mod340_type0.pot
odoo_addons/l10n_es_aeat_mod340_type0/i18n/pt_BR.po
odoo_addons/l10n_es_aeat_mod340_type0/i18n/sl.po
odoo_addons/l10n_es_aeat_mod340_type0/models/__init__.py
odoo_addons/l10n_es_aeat_mod340_type0/models/mod340.py
odoo_addons/l10n_es_aeat_mod340_type0/static/description/icon.png
odoo_addons/l10n_es_aeat_mod340_type0/static/description/icon_source.svg
odoo_addons/l10n_es_aeat_mod340_type0/wizard/__init__.py
odoo_addons/l10n_es_aeat_mod340_type0/wizard/export_mod340_to_boe.py
odoo8_addon_l10n_es_aeat_mod340_type0-8.0.1.0.0.99.dev10.dist-info/METADATA
odoo8_addon_l10n_es_aeat_mod340_type0-8.0.1.0.0.99.dev10.dist-info/WHEEL
odoo8_addon_l10n_es_aeat_mod340_type0-8.0.1.0.0.99.dev10.dist-info/namespace_packages.txt
odoo8_addon_l10n_es_aeat_mod340_type0-8.0.1.0.0.99.dev10.dist-info/top_level.txt
odoo8_addon_l10n_es_aeat_mod340_type0-8.0.1.0.0.99.dev10.dist-info/RECORD
